BrainX/__init__.py
BrainX/tests/test_version.py
brainx-2026.1.31.dist-info/licenses/LICENSE
brainx-2026.1.31.dist-info/METADATA
brainx-2026.1.31.dist-info/WHEEL
brainx-2026.1.31.dist-info/top_level.txt
brainx-2026.1.31.dist-info/RECORD
