Metadata-Version: 2.4
Name: BrainX
Version: 2026.1.31
Summary: Ecosystem for Brain Simulation.
Author-email: BrainX Ecosystem <chao.brain@qq.com>
Project-URL: Documentation, https://brainmodeling.readthedocs.io/
Project-URL: Homepage, https://github.com/chaobrain/brain-modeling-ecosystem
Project-URL: Source Code, https://github.com/chaobrain/brain-modeling-ecosystem
Project-URL: Bug Tracker, https://github.com/chaobrain/brain-modeling-ecosystem/issues
Keywords: computational neuroscience,brain-inspired computation,brain simulation,brain modeling
Classifier: Natural Language :: English
Classifier: Operating System :: OS Independent
Classifier: Programming Language :: Python
Classifier: Programming Language :: Python :: 3
Classifier: Programming Language :: Python :: 3.10
Classifier: Programming Language :: Python :: 3.11
Classifier: Programming Language :: Python :: 3.12
Classifier: Programming Language :: Python :: 3.13
Classifier: Programming Language :: Python :: 3.14
Classifier: Intended Audience :: Science/Research
Classifier: Topic :: Scientific/Engineering :: Bio-Informatics
Classifier: Topic :: Scientific/Engineering :: Mathematics
Classifier: Topic :: Scientific/Engineering :: Artificial Intelligence
Classifier: Topic :: Software Development :: Libraries
Requires-Python: >=3.10
License-File: LICENSE
Requires-Dist: brainunit==0.1.4
Requires-Dist: brainevent==0.0.5
Requires-Dist: brainstate==0.2.10
Requires-Dist: braintools==0.1.8
Requires-Dist: braintrace==0.1.2
Requires-Dist: braincell==0.0.7
Requires-Dist: brainpy==2.7.6
Requires-Dist: brainpy-state==0.0.3
Requires-Dist: brainmass==0.0.5
Requires-Dist: pinnx==0.0.3
Requires-Dist: numpy>=1.15
Requires-Dist: jax<0.9.0,>=0.6.0
Requires-Dist: msgpack>=1.1.0
Requires-Dist: matplotlib
Provides-Extra: cpu
Requires-Dist: jax[cpu]>=0.6.0; extra == "cpu"
Provides-Extra: cuda12
Requires-Dist: jax[cuda12]<0.9.0; extra == "cuda12"
Provides-Extra: cuda13
Requires-Dist: jax[cuda13]<0.9.0; extra == "cuda13"
Provides-Extra: tpu
Requires-Dist: jax[tpu]<0.9.0; extra == "tpu"
Dynamic: license-file
